eark/__init__.py
eark/inhour.py
eark/plot.py
eark/tests/__init__.py
eark/tests/test_inhour.py
eark-0.1.0.dist-info/LICENSE
eark-0.1.0.dist-info/METADATA
eark-0.1.0.dist-info/WHEEL
eark-0.1.0.dist-info/top_level.txt
eark-0.1.0.dist-info/RECORD
