Metadata-Version: 2.1
Name: eark
Version: 0.1.0
Summary: Emulating Astronautical Reactor Kinetics
Home-page: http://github.com/vigneshwar-manickam/eark
Author: Vigneshwar Manickam
Author-email: vigneshwar.manickam@gatech.edu
License: MIT
Platform: UNKNOWN
